{"name": "South Carolina","children": [{"name": "Accommodation and Food Services", "children": [{"name": "29 Full-Service Restaurants", "size": 29}, {"name": "17 Limited-Service Restaurants", "size": 17}, {"name": "6 Hotels (except Casino Hotels) and Motels", "size": 6}, {"name": "2 Food Service Contractors", "size": 2}, {"name": "1 All Other Traveler Accommodation", "size": 1}, {"name": "1 Limited-Service Eating Places", "size": 1}]}, {"name": "Administrative and Support and Waste Management and Remediation Services", "children": [{"name": "274 Janitorial Services", "size": 274}, {"name": "3 Professional Employer Organizations", "size": 3}, {"name": "2 Temporary Help Services", "size": 2}, {"name": "2 Travel Agencies", "size": 2}, {"name": "1 Business Support Services", "size": 1}, {"name": "1 Employment Services", "size": 1}, {"name": "1 Facilities Support Services", "size": 1}, {"name": "1 Landscaping Services", "size": 1}, {"name": "1 Office Administrative Services", "size": 1}, {"name": "1 Other", "size": 1}, {"name": "1 Tour Operators", "size": 1}]}, {"name": "Agriculture, Forestry, Fishing and Hunting", "children": [{"name": "53 Noncitrus Fruit and Tree Nut Farming", "size": 53}, {"name": "2 Horses and Other Equine Production", "size": 2}, {"name": "2 Support Activities for Animal Production", "size": 2}, {"name": "1 Berry (except Strawberry) Farming", "size": 1}, {"name": "1 Greenhouse, Nursery, and Floriculture Production", "size": 1}, {"name": "1 Other Vegetable (except Potato) and Melon Farming", "size": 1}, {"name": "1 Vegetable and Melon Farming", "size": 1}]}, {"name": "Air Transportation", "children": [{"name": "3 Scheduled Passenger Air Transportation", "size": 3}, {"name": "2 Scheduled Air Transportation", "size": 2}, {"name": "1 Other Nonscheduled Air Transportation", "size": 1}]}, {"name": "Apparel Manufacturing", "children": [{"name": "2 Other Apparel Accessories and Other Apparel Manufacturing", "size": 2}]}, {"name": "Arts, Entertainment, and Recreation", "children": [{"name": "1 Musical Groups and Artists", "size": 1}, {"name": "1 Other Performing Arts Companies", "size": 1}]}, {"name": "Beverage and Tobacco Product Manufacturing", "children": [{"name": "1 Breweries", "size": 1}, {"name": "1 Soft Drink Manufacturing", "size": 1}, {"name": "1 Wineries", "size": 1}]}, {"name": "Building Material and Garden Equipment and Supplies Dealers", "children": [{"name": "1 Home Centers", "size": 1}, {"name": "1 Other Building Material Dealers", "size": 1}]}, {"name": "Chemical Manufacturing", "children": [{"name": "8 Pharmaceutical Preparation Manufacturing", "size": 8}, {"name": "7 Pharmaceutical and Medicine Manufacturing", "size": 7}, {"name": "5 Plastics Material and Resin Manufacturing", "size": 5}, {"name": "4 Medicinal and Botanical Manufacturing", "size": 4}, {"name": "3 All Other Basic Organic Chemical Manufacturing", "size": 3}, {"name": "3 Petrochemical Manufacturing", "size": 3}, {"name": "1 All Other Basic Inorganic Chemical Manufacturing", "size": 1}, {"name": "1 Biological Product (except Diagnostic) Manufacturing", "size": 1}, {"name": "1 Noncellulosic Organic Fiber Manufacturing", "size": 1}, {"name": "1 Paint and Coating Manufacturing", "size": 1}, {"name": "1 Photographic Film, Paper, Plate, and Chemical Manufacturing", "size": 1}, {"name": "1 Surface Active Agent Manufacturing", "size": 1}, {"name": "1 Toilet Preparation Manufacturing", "size": 1}]}, {"name": "Clothing and Clothing Accessories Stores", "children": [{"name": "3 Other Clothing Stores", "size": 3}, {"name": "2 Jewelry Stores", "size": 2}, {"name": "1 Clothing Accessories Stores", "size": 1}, {"name": "1 Clothing Stores", "size": 1}, {"name": "1 Women's Clothing Stores", "size": 1}]}, {"name": "Computer and Electronic Product Manufacturing", "children": [{"name": "48 Semiconductor and Other Electronic Component Manufacturing", "size": 48}, {"name": "21 Radio and Television Broadcasting and Wireless Communications Equipment Manufacturing", "size": 21}, {"name": "20 Electronic Computer Manufacturing", "size": 20}, {"name": "17 Semiconductor and Related Device Manufacturing", "size": 17}, {"name": "7 Instrument Manufacturing for Measuring and Testing Electricity and Electrical Signals", "size": 7}, {"name": "4 Electromedical and Electrotherapeutic Apparatus Manufacturing", "size": 4}, {"name": "4 Instruments and Related Products Manufacturing for Measuring, Displaying, and Controlling Industrial Process Variables", "size": 4}, {"name": "3 Other Communications Equipment Manufacturing", "size": 3}, {"name": "3 Other Computer Peripheral Equipment Manufacturing", "size": 3}, {"name": "2 Automatic Environmental Control Manufacturing for Residential, Commercial, and Appliance Use", "size": 2}, {"name": "2 Communications Equipment Manufacturing", "size": 2}, {"name": "2 Other Electronic Component Manufacturing", "size": 2}, {"name": "1 Computer Storage Device Manufacturing", "size": 1}, {"name": "1 Electronic Capacitor Manufacturing", "size": 1}, {"name": "1 Telephone Apparatus Manufacturing", "size": 1}]}, {"name": "Construction", "children": [{"name": "5 Drywall and Insulation Contractors", "size": 5}, {"name": "4 Residential Building Construction", "size": 4}, {"name": "3 Other Heavy and Civil Engineering Construction", "size": 3}, {"name": "2 All Other Specialty Trade Contractors", "size": 2}, {"name": "2 Commercial and Institutional Building Construction", "size": 2}, {"name": "2 Industrial Building Construction", "size": 2}, {"name": "2 Masonry Contractors", "size": 2}, {"name": "1 Construction of Buildings", "size": 1}, {"name": "1 Electrical Contractors", "size": 1}, {"name": "1 Glass and Glazing Contractors", "size": 1}, {"name": "1 New Multifamily Housing Construction (except Operative Builders)", "size": 1}, {"name": "1 Painting and Wall Covering Contractors", "size": 1}, {"name": "1 Power and Communication Line and Related Structures Construction", "size": 1}, {"name": "1 Water and Sewer Line and Related Structures Construction", "size": 1}]}, {"name": "Couriers and Messengers", "children": [{"name": "1 Local Messengers and Local Delivery", "size": 1}]}, {"name": "Educational Services", "children": [{"name": "129 Colleges, Universities, and Professional Schools", "size": 129}, {"name": "81 Elementary and Secondary Schools", "size": 81}, {"name": "12 Educational Support Services", "size": 12}, {"name": "4 Sports and Recreation Instruction", "size": 4}, {"name": "1 Business and Secretarial Schools", "size": 1}, {"name": "1 Technical and Trade Schools", "size": 1}]}, {"name": "Electrical Equipment, Appliance, and Component Manufacturing", "children": [{"name": "5 Household Appliance Manufacturing", "size": 5}, {"name": "4 Commercial, Industrial, and Institutional Electric Lighting Fixture Manufacturing", "size": 4}, {"name": "3 Power, Distribution, and Specialty Transformer Manufacturing", "size": 3}, {"name": "2 All Other Miscellaneous Electrical Equipment and Component Manufacturing", "size": 2}, {"name": "2 Relay and Industrial Control Manufacturing", "size": 2}, {"name": "1 Electric Lamp Bulb and Part Manufacturing", "size": 1}, {"name": "1 Electric Lighting Equipment Manufacturing", "size": 1}, {"name": "1 Electrical Equipment Manufacturing", "size": 1}, {"name": "1 Fiber Optic Cable Manufacturing", "size": 1}, {"name": "1 Major Appliance Manufacturing", "size": 1}, {"name": "1 Motor and Generator Manufacturing", "size": 1}, {"name": "1 Storage Battery Manufacturing", "size": 1}]}, {"name": "Electronics and Appliance Stores", "children": [{"name": "1 Computer and Software Stores", "size": 1}]}, {"name": "Fabricated Metal Product Manufacturing", "children": [{"name": "7 Ball and Roller Bearing Manufacturing", "size": 7}, {"name": "1 Hand and Edge Tool Manufacturing", "size": 1}, {"name": "1 Machine Shops", "size": 1}, {"name": "1 Plumbing Fixture Fitting and Trim Manufacturing", "size": 1}, {"name": "1 Power Boiler and Heat Exchanger Manufacturing", "size": 1}]}, {"name": "Finance and Insurance", "children": [{"name": "17 Investment Banking and Securities Dealing", "size": 17}, {"name": "11 Financial Transactions Processing, Reserve, and Clearinghouse Activities", "size": 11}, {"name": "8 Insurance Carriers", "size": 8}, {"name": "6 Commercial Banking", "size": 6}, {"name": "6 Credit Card Issuing", "size": 6}, {"name": "6 Direct Life, Health, and Medical Insurance Carriers", "size": 6}, {"name": "5 Direct Health and Medical Insurance Carriers", "size": 5}, {"name": "4 Mortgage and Nonmortgage Loan Brokers", "size": 4}, {"name": "3 Direct Life Insurance Carriers", "size": 3}, {"name": "3 Insurance Agencies and Brokerages", "size": 3}, {"name": "3 Portfolio Management", "size": 3}, {"name": "2 Miscellaneous Financial Investment Activities", "size": 2}, {"name": "2 Secondary Market Financing", "size": 2}, {"name": "1 All Other Insurance Related Activities", "size": 1}, {"name": "1 All Other Nondepository Credit Intermediation", "size": 1}, {"name": "1 Direct Property and Casualty Insurance Carriers", "size": 1}, {"name": "1 Insurance and Employee Benefit Funds", "size": 1}, {"name": "1 Investment Advice", "size": 1}, {"name": "1 Miscellaneous Intermediation", "size": 1}, {"name": "1 Other Financial Vehicles", "size": 1}, {"name": "1 Pension Funds", "size": 1}, {"name": "1 Third Party Administration of Insurance and Pension Funds", "size": 1}]}, {"name": "Food and Beverage Stores", "children": [{"name": "3 Convenience Stores", "size": 3}, {"name": "2 Supermarkets and Other Grocery (except Convenience) Stores", "size": 2}, {"name": "1 All Other Specialty Food Stores", "size": 1}, {"name": "1 Grocery Stores", "size": 1}]}, {"name": "Food Manufacturing", "children": [{"name": "600 Poultry Processing", "size": 600}, {"name": "4 Other Food Manufacturing", "size": 4}, {"name": "2 Meat Processed from Carcasses", "size": 2}, {"name": "1 All Other Miscellaneous Food Manufacturing", "size": 1}, {"name": "1 Animal (except Poultry) Slaughtering", "size": 1}, {"name": "1 Animal Food Manufacturing", "size": 1}, {"name": "1 Fluid Milk Manufacturing", "size": 1}, {"name": "1 Food Manufacturing", "size": 1}, {"name": "1 Fresh and Frozen Seafood Processing", "size": 1}]}, {"name": "Furniture and Home Furnishings Stores", "children": [{"name": "2 Furniture Stores", "size": 2}]}, {"name": "Gasoline Stations", "children": [{"name": "7 Gasoline Stations with Convenience Stores", "size": 7}]}, {"name": "General Merchandise Stores", "children": [{"name": "3 Discount Department Stores", "size": 3}, {"name": "1 All Other General Merchandise Stores", "size": 1}]}, {"name": "Health and Personal Care Stores", "children": [{"name": "6 Pharmacies and Drug Stores", "size": 6}, {"name": "1 Cosmetics, Beauty Supplies, and Perfume Stores", "size": 1}, {"name": "1 Food (Health) Supplement Stores", "size": 1}]}, {"name": "Health Care and Social Assistance", "children": [{"name": "59 Offices of Physicians (except Mental Health Specialists)", "size": 59}, {"name": "24 General Medical and Surgical Hospitals", "size": 24}, {"name": "10 Home Health Care Services", "size": 10}, {"name": "8 Offices of Dentists", "size": 8}, {"name": "7 Offices of Physical, Occupational and Speech Therapists, and Audiologists", "size": 7}, {"name": "2 Hospitals", "size": 2}, {"name": "2 Nursing Care Facilities", "size": 2}, {"name": "2 Offices of All Other Health Practitioners", "size": 2}, {"name": "2 Offices of Physicians, Mental Health Specialists", "size": 2}, {"name": "2 Other Individual and Family Services", "size": 2}, {"name": "1 All Other Ambulatory Health Care Services", "size": 1}, {"name": "1 All Other Miscellaneous Ambulatory Health Care Services", "size": 1}, {"name": "1 Health Care and Social Assistance", "size": 1}, {"name": "1 HMO Medical Centers", "size": 1}, {"name": "1 Individual and Family Services", "size": 1}, {"name": "1 Medical and Diagnostic Laboratories", "size": 1}, {"name": "1 Offices of Physicians", "size": 1}, {"name": "1 Residential Mental Retardation Facilities", "size": 1}, {"name": "1 Specialty (except Psychiatric and Substance Abuse) Hospitals", "size": 1}]}, {"name": "Information", "children": [{"name": "54 Software Publishers", "size": 54}, {"name": "12 Web Search Portals", "size": 12}, {"name": "10 Data Processing, Hosting, and Related Services", "size": 10}, {"name": "4 Cellular and Other Wireless Telecommunications", "size": 4}, {"name": "4 Internet Publishing and Broadcasting", "size": 4}, {"name": "4 Newspaper Publishers", "size": 4}, {"name": "4 Other Telecommunications", "size": 4}, {"name": "3 Internet Service Providers", "size": 3}, {"name": "2 All Other Information Services", "size": 2}, {"name": "2 Other Information Services", "size": 2}, {"name": "1 Integrated Record Production/Distribution", "size": 1}, {"name": "1 Internet Service Providers and Web Search Portals", "size": 1}, {"name": "1 News Syndicates", "size": 1}, {"name": "1 Other", "size": 1}, {"name": "1 Radio Broadcasting", "size": 1}, {"name": "1 Telecommunications", "size": 1}, {"name": "1 Television Broadcasting", "size": 1}]}, {"name": "Machinery Manufacturing", "children": [{"name": "21 Engine, Turbine, and Power Transmission Equipment Manufacturing", "size": 21}, {"name": "4 Oil and Gas Field Machinery and Equipment Manufacturing", "size": 4}, {"name": "3 All Other Industrial Machinery Manufacturing", "size": 3}, {"name": "3 Construction Machinery Manufacturing", "size": 3}, {"name": "3 Machine Tool (Metal Cutting Types) Manufacturing", "size": 3}, {"name": "3 Optical Instrument and Lens Manufacturing", "size": 3}, {"name": "3 Turbine and Turbine Generator Set Units Manufacturing", "size": 3}, {"name": "2 Industrial Machinery Manufacturing", "size": 2}, {"name": "2 Power-Driven Handtool Manufacturing", "size": 2}, {"name": "1 Air Purification Equipment Manufacturing", "size": 1}, {"name": "1 All Other General Purpose Machinery Manufacturing", "size": 1}, {"name": "1 All Other Miscellaneous General Purpose Machinery Manufacturing", "size": 1}, {"name": "1 Cutting Tool and Machine Tool Accessory Manufacturing", "size": 1}, {"name": "1 Heating Equipment (except Warm Air Furnaces) Manufacturing", "size": 1}, {"name": "1 Mechanical Power Transmission Equipment Manufacturing", "size": 1}, {"name": "1 Other Commercial and Service Industry Machinery Manufacturing", "size": 1}, {"name": "1 Other Engine Equipment Manufacturing", "size": 1}, {"name": "1 Semiconductor Machinery Manufacturing", "size": 1}, {"name": "1 Ventilation, Heating, Air-Conditioning, and Commercial Refrigeration Equipment Manufacturing", "size": 1}]}, {"name": "Management of Companies and Enterprises", "children": [{"name": "5 Offices of Other Holding Companies", "size": 5}, {"name": "1 Management of Companies and Enterprises", "size": 1}]}, {"name": "Mining, Quarrying, and Oil and Gas Extraction", "children": [{"name": "1 Support Activities for Oil and Gas Operations", "size": 1}]}, {"name": "Miscellaneous Manufacturing", "children": [{"name": "4 Medical Equipment and Supplies Manufacturing", "size": 4}, {"name": "3 All Other Miscellaneous Manufacturing", "size": 3}, {"name": "3 Sporting and Athletic Goods Manufacturing", "size": 3}, {"name": "1 Surgical and Medical Instrument Manufacturing", "size": 1}]}, {"name": "Miscellaneous Store Retailers", "children": [{"name": "1 All Other Miscellaneous Store Retailers", "size": 1}, {"name": "1 Gift, Novelty, and Souvenir Stores", "size": 1}, {"name": "1 Office Supplies and Stationery Stores", "size": 1}]}, {"name": "Motor Vehicle and Parts Dealers", "children": [{"name": "1 Automotive Parts and Accessories Stores", "size": 1}, {"name": "1 Tire Dealers", "size": 1}]}, {"name": "Nonmetallic Mineral Product Manufacturing", "children": [{"name": "4 Cement Manufacturing", "size": 4}, {"name": "3 Other Pressed and Blown Glass and Glassware Manufacturing", "size": 3}]}, {"name": "Nonstore Retailers", "children": [{"name": "25 Electronic Shopping", "size": 25}, {"name": "4 Electronic Auctions", "size": 4}, {"name": "1 Fuel Dealers", "size": 1}]}, {"name": "Other Services (except Public Administration)", "children": [{"name": "9 Religious Organizations", "size": 9}, {"name": "3 Drycleaning and Laundry Services (except Coin-Operated)", "size": 3}, {"name": "3 Other Automotive Mechanical and Electrical Repair and Maintenance", "size": 3}, {"name": "2 Nail Salons", "size": 2}, {"name": "1 All Other Personal Services", "size": 1}, {"name": "1 Automotive Body, Paint, Interior, and Glass Repair", "size": 1}, {"name": "1 Automotive Repair and Maintenance", "size": 1}, {"name": "1 Commercial and Industrial Machinery and Equipment (except Automotive and Electronic) Repair and Maintenance", "size": 1}, {"name": "1 Hair, Nail, and Skin Care Services", "size": 1}, {"name": "1 Other Electronic and Precision Equipment Repair and Maintenance", "size": 1}, {"name": "1 Other Personal Care Services", "size": 1}, {"name": "1 Private Households", "size": 1}]}, {"name": "Paper Manufacturing", "children": [{"name": "3 Paper (except Newsprint) Mills", "size": 3}, {"name": "2 Converted Paper Product Manufacturing", "size": 2}, {"name": "1 Pulp, Paper, and Paperboard Mills", "size": 1}]}, {"name": "Petroleum and Coal Products Manufacturing", "children": [{"name": "1 Asphalt Paving Mixture and Block Manufacturing", "size": 1}, {"name": "1 Petroleum Lubricating Oil and Grease Manufacturing", "size": 1}]}, {"name": "Plastics and Rubber Products Manufacturing", "children": [{"name": "2 All Other Plastics Product Manufacturing", "size": 2}, {"name": "1 All Other Rubber Product Manufacturing", "size": 1}, {"name": "1 Plastics Product Manufacturing", "size": 1}]}, {"name": "Primary Metal Manufacturing", "children": [{"name": "2 Iron and Steel Mills", "size": 2}, {"name": "1 Iron and Steel Pipe and Tube Manufacturing from Purchased Steel", "size": 1}, {"name": "1 Nonferrous Metal (except Aluminum) Smelting and Refining", "size": 1}, {"name": "1 Secondary Smelting, Refining, and Alloying of Nonferrous Metal (except Copper and Aluminum)", "size": 1}]}, {"name": "Printing and Related Support Activities", "children": [{"name": "2 Commercial Gravure Printing", "size": 2}, {"name": "1 Other Commercial Printing", "size": 1}, {"name": "1 Printing", "size": 1}]}, {"name": "Professional, Scientific, and Technical Services", "children": [{"name": "308 Custom Computer Programming Services", "size": 308}, {"name": "164 Computer Systems Design Services", "size": 164}, {"name": "52 Engineering Services", "size": 52}, {"name": "38 Other Computer Related Services", "size": 38}, {"name": "26 Computer Systems Design and Related Services", "size": 26}, {"name": "17 Administrative Management and General Management Consulting Services", "size": 17}, {"name": "12 All Other Professional, Scientific, and Technical Services", "size": 12}, {"name": "11 Management, Scientific, and Technical Consulting Services", "size": 11}, {"name": "11 Research and Development in the Physical, Engineering, and Life Sciences", "size": 11}, {"name": "8 Marketing Consulting Services", "size": 8}, {"name": "7 Veterinary Services", "size": 7}, {"name": "5 Computer Facilities Management Services", "size": 5}, {"name": "5 Offices of Certified Public Accountants", "size": 5}, {"name": "5 Other Scientific and Technical Consulting Services", "size": 5}, {"name": "4 Offices of Lawyers", "size": 4}, {"name": "4 Process, Physical Distribution, and Logistics Consulting Services", "size": 4}, {"name": "3 Accounting, Tax Preparation, Bookkeeping, and Payroll Services", "size": 3}, {"name": "3 Management Consulting Services", "size": 3}, {"name": "3 Other", "size": 3}, {"name": "3 Testing Laboratories", "size": 3}, {"name": "2 Advertising and Related Services", "size": 2}, {"name": "2 Architectural Services", "size": 2}, {"name": "2 Environmental Consulting Services", "size": 2}, {"name": "2 Geophysical Surveying and Mapping Services", "size": 2}, {"name": "2 Industrial Design Services", "size": 2}, {"name": "2 Other Accounting Services", "size": 2}, {"name": "2 Other Management Consulting Services", "size": 2}, {"name": "1 Advertising, Public Relations, and Related Services", "size": 1}, {"name": "1 Interior Design Services", "size": 1}, {"name": "1 Marketing Research and Public Opinion Polling", "size": 1}, {"name": "1 Other Professional, Scientific, and Technical Services", "size": 1}, {"name": "1 Other Services Related to Advertising", "size": 1}, {"name": "1 Payroll Services", "size": 1}, {"name": "1 Research and Development in the Social Sciences and Humanities", "size": 1}]}, {"name": "Public Administration", "children": [{"name": "1 Public Finance Activities", "size": 1}]}, {"name": "Real Estate and Rental and Leasing", "children": [{"name": "7 Other Activities Related to Real Estate", "size": 7}, {"name": "1 Consumer Electronics and Appliances Rental", "size": 1}, {"name": "1 Offices of Real Estate Agents and Brokers", "size": 1}]}, {"name": "Sporting Goods, Hobby, Book, and Music Stores", "children": [{"name": "1 Sporting Goods Stores", "size": 1}]}, {"name": "Support Activities for Transportation", "children": [{"name": "2 Freight Transportation Arrangement", "size": 2}, {"name": "2 Marine Cargo Handling", "size": 2}, {"name": "1 Other Support Activities for Air Transportation", "size": 1}, {"name": "1 Other Support Activities for Water Transportation", "size": 1}, {"name": "1 Support Activities for Rail Transportation", "size": 1}]}, {"name": "Textile Mills", "children": [{"name": "2 Textile and Fabric Finishing (except Broadwoven Fabric) Mills", "size": 2}, {"name": "1 Knit Fabric Mills", "size": 1}, {"name": "1 Textile and Fabric Finishing and Fabric Coating Mills", "size": 1}, {"name": "1 Thread Mills", "size": 1}]}, {"name": "Transportation Equipment Manufacturing", "children": [{"name": "6 Motor Vehicle Transmission and Power Train Parts Manufacturing", "size": 6}, {"name": "5 All Other Motor Vehicle Parts Manufacturing", "size": 5}, {"name": "5 Gasoline Engine and Engine Parts Manufacturing", "size": 5}, {"name": "4 Aircraft Manufacturing", "size": 4}, {"name": "4 Motor Vehicle Body Manufacturing", "size": 4}, {"name": "4 Motor Vehicle Parts Manufacturing", "size": 4}, {"name": "3 Motor Vehicle Seating and Interior Trim Manufacturing", "size": 3}, {"name": "2 Automobile Manufacturing", "size": 2}, {"name": "2 Heavy Duty Truck Manufacturing", "size": 2}, {"name": "2 Motor Vehicle Brake System Manufacturing", "size": 2}, {"name": "1 Aerospace Product and Parts Manufacturing", "size": 1}, {"name": "1 Boat Building", "size": 1}, {"name": "1 Motor Vehicle Gasoline Engine and Engine Parts Manufacturing", "size": 1}, {"name": "1 Motor Vehicle Metal Stamping", "size": 1}]}, {"name": "Truck Transportation", "children": [{"name": "1 General Freight Trucking, Long-Distance", "size": 1}]}, {"name": "Unknown", "children": [{"name": "14 Other", "size": 14}]}, {"name": "Utilities", "children": [{"name": "2 Electric Power Distribution", "size": 2}, {"name": "1 Electric Bulk Power Transmission and Control", "size": 1}, {"name": "1 Electric Power Generation", "size": 1}, {"name": "1 Electric Power Generation, Transmission and Distribution", "size": 1}]}, {"name": "Wholesale Trade", "children": [{"name": "8 Computer and Computer Peripheral Equipment and Software Merchant Wholesalers", "size": 8}, {"name": "4 Men's and Boys' Clothing and Furnishings Merchant Wholesalers", "size": 4}, {"name": "3 Drugs and Druggists' Sundries Merchant Wholesalers", "size": 3}, {"name": "3 Grocery and Related Product Wholesalers", "size": 3}, {"name": "2 Jewelry, Watch, Precious Stone, and Precious Metal Merchant Wholesalers", "size": 2}, {"name": "2 Other Chemical and Allied Products Merchant Wholesalers", "size": 2}, {"name": "2 Other Electronic Parts and Equipment Merchant Wholesalers", "size": 2}, {"name": "2 Other Miscellaneous Durable Goods Merchant Wholesalers", "size": 2}, {"name": "2 Other Miscellaneous Nondurable Goods Merchant Wholesalers", "size": 2}, {"name": "1 Apparel, Piece Goods, and Notions Merchant Wholesalers", "size": 1}, {"name": "1 Book, Periodical, and Newspaper Merchant Wholesalers", "size": 1}, {"name": "1 Business to Business Electronic Markets", "size": 1}, {"name": "1 Electrical and Electronic Goods Merchant Wholesalers", "size": 1}, {"name": "1 Fresh Fruit and Vegetable Merchant Wholesalers", "size": 1}, {"name": "1 Furniture Merchant Wholesalers", "size": 1}, {"name": "1 Home Furnishing Merchant Wholesalers", "size": 1}, {"name": "1 Industrial and Personal Service Paper Merchant Wholesalers", "size": 1}, {"name": "1 Industrial Machinery and Equipment Merchant Wholesalers", "size": 1}, {"name": "1 Meat and Meat Product Merchant Wholesalers", "size": 1}, {"name": "1 Office Equipment Merchant Wholesalers", "size": 1}, {"name": "1 Other Commercial Equipment Merchant Wholesalers", "size": 1}, {"name": "1 Other Grocery and Related Products Merchant Wholesalers", "size": 1}, {"name": "1 Packaged Frozen Food Merchant Wholesalers", "size": 1}, {"name": "1 Transportation Equipment and Supplies (except Motor Vehicle) Merchant Wholesalers", "size": 1}, {"name": "1 Women's, Children's, and Infants' Clothing and Accessories Merchant Wholesalers", "size": 1}]}]}